gto/__init__.py
gto/api.py
gto/base.py
gto/branch.py
gto/cli.py
gto/commit.py
gto/config.py
gto/constants.py
gto/exceptions.py
gto/index.py
gto/log.py
gto/registry.py
gto/tag.py
gto/utils.py
gto/versions.py
great_tool_ops-0.0.7.dist-info/METADATA
great_tool_ops-0.0.7.dist-info/WHEEL
great_tool_ops-0.0.7.dist-info/entry_points.txt
great_tool_ops-0.0.7.dist-info/top_level.txt
great_tool_ops-0.0.7.dist-info/RECORD
