Metadata-Version: 2.1
Name: great-tool-ops
Version: 0.0.7
Summary: Version and deploy your models following GitOps principles
Home-page: UNKNOWN
Author: Alexander Guschin
Author-email: aguschin@iterative.ai
License: Apache License 2.0
Download-URL: https://github.com/iterative/gto
Keywords: git gto mlops artifact registry developer-tools collaboration
Platform: UNKNOWN
Classifier: Development Status :: 2 - Pre-Alpha
Classifier: Programming Language :: Python :: 3
Classifier: Programming Language :: Python :: 3.6
Classifier: Programming Language :: Python :: 3.7
Classifier: Programming Language :: Python :: 3.8
Classifier: Programming Language :: Python :: 3.9
Requires-Python: >=3.6
Requires-Dist: gitpython
Requires-Dist: click
Requires-Dist: pandas
Requires-Dist: numpy
Requires-Dist: pydantic
Requires-Dist: ruamel.yaml
Requires-Dist: semver (==3.0.0-dev.3)
Requires-Dist: tabulate (==0.8.9)
Provides-Extra: tests
Requires-Dist: pytest ; extra == 'tests'
Requires-Dist: pytest-cov ; extra == 'tests'
Requires-Dist: pytest-lazy-fixture (==0.6.3) ; extra == 'tests'
Requires-Dist: pytest-mock ; extra == 'tests'
Requires-Dist: pylint ; extra == 'tests'
Requires-Dist: pylint-pytest ; extra == 'tests'
Requires-Dist: pylint-plugin-utils ; extra == 'tests'
